Workbook

Sheet Summary
A1: PinLocal Launch Budget
A2: Monthly cost planning workbook for launch, one-city growth, and scale-up.
A4: Scenario | B4: Infra USD | C4: Variable USD | D4: Total USD | E4: Total INR | F4: Launch note
A5: Friends Testing | B5: =Scenarios!B17 | C5: =Scenarios!B18 | D5: =Scenarios!B19 | E5: =Scenarios!B20 | F5: Good for testing panels with friends before real public launch.
A6: Soft Launch | B6: =Scenarios!C17 | C6: =Scenarios!C18 | D6: =Scenarios!C19 | E6: =Scenarios!C20 | F6: Lowest paid stack that still looks launch-shaped.
A7: One City Launch | B7: =Scenarios!D17 | C7: =Scenarios!D18 | D7: =Scenarios!D19 | E7: =Scenarios!D20 | F7: Best recommended production-style starting point.
A8: Growth Mode | B8: =Scenarios!E17 | C8: =Scenarios!E18 | D8: =Scenarios!E19 | E8: =Scenarios!E20 | F8: Early scale-up planning, not day-one spend.
A11: What this means
A12: Current must-pay unlock | B12: Upstash Fixed 250MB | C12: $10/mo | D12: Needed because your free Redis request limit is already exhausted.
A13: Recommended launch stack | B13: Frontend Starter + Backend Standard + Upstash Fixed + Postgres 1GB | C13: =Scenarios!D19 | D13: Good balance for launch without overspending too early.
A14: Biggest unknown | B14: OTP cost | C14: Editable | D14: MSG91 pricing should be filled in once your plan or credit pack is finalized.

Sheet Assumptions
A1: PinLocal Launch Budget Assumptions
A2: Editable inputs for infra, media, and placeholder market-dependent costs.
A4: Category | B4: Item | C4: Unit | D4: USD / Value | E4: Notes
A5: FX | B5: USD to INR | C5: INR per USD | D5: 84 | E5: Editable exchange-rate assumption.
A6: Render | B6: Frontend Starter | C6: USD / month | D6: 7 | E6: Frontend web service.
A7: Render | B7: Backend Starter | C7: USD / month | D7: 7 | E7: Cheapest workable backend for private testing.
A8: Render | B8: Backend Standard | C8: USD / month | D8: 25 | E8: Recommended for real city launch with chat and media.
A9: Render | B9: Backend Pro | C9: USD / month | D9: 85 | E9: Scale-up option once concurrency and jobs grow.
A10: Upstash | B10: Redis Fixed 250MB | C10: USD / month | D10: 10 | E10: Recommended because free tier already hit request limit.
A11: Render | B11: Postgres 256MB | C11: USD / month | D11: 6 | E11: Low-end managed DB option.
A12: Render | B12: Postgres 1GB | C12: USD / month | D12: 19 | E12: Practical managed DB option for launch.
A13: Render | B13: Postgres 4GB | C13: USD / month | D13: 75 | E13: Growth-stage DB option.
A14: Cloudflare R2 | B14: Media budget - friends testing | C14: USD / month | D14: 0 | E14: R2 is often free at this stage.
A15: Cloudflare R2 | B15: Media budget - soft launch | C15: USD / month | D15: 2 | E15: Light image/video usage buffer.
A16: Cloudflare R2 | B16: Media budget - one city launch | C16: USD / month | D16: 5 | E16: Useful planning placeholder.
... A23: Taxes | B23: Taxes / GST placeholder | C23: USD / month | D23: 0 | E23: Keep zero until exact billing country tax is known.
A26: Planning note | B26: Totals in this model are strong for infra planning, but OTP and exact domain tax will need one more pass before launch because those are vendor- and region-dependent.

Sheet Scenarios
A1: Launch Scenarios
A2: Four planning modes: from testing with friends to broader growth. All totals are formula-driven from the Assumptions tab.
A4: Cost line | B4: Friends Testing | C4: Soft Launch | D4: One City Launch | E4: Growth Mode
A5: Render frontend Starter | B5: =Assumptions!$D$6 | C5: =Assumptions!$D$6 | D5: =Assumptions!$D$6 | E5: =Assumptions!$D$6
A6: Render backend Starter | B6: =Assumptions!$D$7 | C6: =Assumptions!$D$7 | D6: 0 | E6: 0
A7: Render backend Standard | B7: 0 | C7: 0 | D7: =Assumptions!$D$8 | E7: 0
A8: Render backend Pro | B8: 0 | C8: 0 | D8: 0 | E8: =Assumptions!$D$9
A9: Upstash Redis Fixed 250MB | B9: =Assumptions!$D$10 | C9: =Assumptions!$D$10 | D9: =Assumptions!$D$10 | E9: =Assumptions!$D$10
A10: Render Postgres 256MB | B10: 0 | C10: =Assumptions!$D$11 | D10: 0 | E10: 0
A11: Render Postgres 1GB | B11: 0 | C11: 0 | D11: =Assumptions!$D$12 | E11: 0
A12: Render Postgres 4GB | B12: 0 | C12: 0 | D12: 0 | E12: =Assumptions!$D$13
A13: Cloudflare R2 media budget | B13: =Assumptions!$D$14 | C13: =Assumptions!$D$15 | D13: =Assumptions!$D$16 | E13: =Assumptions!$D$17
A14: OTP budget (editable) | B14: =Assumptions!$D$18 | C14: =Assumptions!$D$19 | D14: =Assumptions!$D$20 | E14: =Assumptions!$D$21
A15: Domain budget | B15: =Assumptions!$D$22 | C15: =Assumptions!$D$22 | D15: =Assumptions!$D$22 | E15: =Assumptions!$D$22
A16: Taxes / GST placeholder | B16: =Assumptions!$D$23 | C16: =Assumptions!$D$23 | D16: =Assumptions!$D$23 | E16: =Assumptions!$D$23
A17: Known infra total (USD) | B17: =SUM(B5:B13) | C17: =SUM(C5:C13) | D17: =SUM(D5:D13) | E17: =SUM(E5:E13)
A18: Editable / market-dependent total (USD) | B18: =SUM(B14:B16) | C18: =SUM(C14:C16) | D18: =SUM(D14:D16) | E18: =SUM(E14:E16)
A19: Projected monthly total (USD) | B19: =B17+B18 | C19: =C17+C18 | D19: =D17+D18 | E19: =E17+E18
A20: Projected monthly total (INR) | B20: =B19*Assumptions!$D$5 | C20: =C19*Assumptions!$D$5 | D20: =D19*Assumptions!$D$5 | E20: =E19*Assumptions!$D$5
A22: Recommended live setup | B22: For a real city launch, the strongest balance is usually Render Frontend Starter + Render Backend Standard + Upstash Fixed 250MB + Render Postgres 1GB, with OTP finalized separately.

Sheet Subscriptions
A1: Subscriptions To Buy
A2: Clean list of what you need first, what can wait, and why.
A4: Priority | B4: Service | C4: Recommended plan | D4: Why
A5: Buy now | B5: Upstash Redis | C5: Fixed 250MB | D5: Free quota is already exhausted, so Redis is the first paid unlock.
A6: Buy now | B6: Render Frontend | C6: Starter | D6: Enough for the website frontend at launch.
A7: Buy now | B7: Render Backend | C7: Standard | D7: Safer for chat, uploads, sockets, OTP, and jobs.
A8: Buy now / optional | B8: Managed Postgres | C8: Render Postgres 1GB | D8: Use this if you want a cleaner single-vendor launch setup.
A9: Later | B9: Cloudflare R2 | C9: Pay only for usage | D9: Usually tiny spend at the beginning, but it is the right long-term media layer.
A10: Later | B10: Backend upgrade | C10: Render Pro | D10: Only when one-city traffic starts pushing CPU, workers, or concurrency.
A11: Later | B11: Higher DB plan | C11: Postgres 4GB | D11: Only when storage, connections, or query load demand it.

Sheet Sources
A1: Pricing Sources
A2: Official links used or referenced for this planning workbook.
A4: Vendor | B4: URL | C4: Comment
A5: Render | B5: https://render.com/pricing | C5: Frontend, backend, Postgres pricing references.
A6: Upstash | B6: https://upstash.com/pricing | C6: Redis fixed plan and free-tier request limit context.
A7: Cloudflare R2 | B7: https://developers.cloudflare.com/r2/pricing/ | C7: Usage-based media storage pricing.
A8: Supabase | B8: https://supabase.com/pricing | C8: Keep as a check if you stay on Supabase instead of moving DB.
A9: MSG91 OTP | B9: https://msg91.com/in/otp | C9: Use dashboard/sales confirmation for final OTP numbers.
